fifids/__init__.py
fifids/api/__init__.py
fifids/api/encoders/__init__.py
fifids/api/encoders/label.py
fifids/api/encoders/one_hot.py
fifids/api/fifi.py
fifids/api/outliers/__init__.py
fifids/api/outliers/outliers.py
fifids/api/pipeline/__init__.py
fifids/api/pipeline/pipeline.py
fifids/api/plot.py
fifids/api/plots/__init__.py
fifids/api/plots/correlation.py
fifids/api/plots/distribution.py
fifids/api/plots/time_series.py
fifids/utility/__init__.py
fifids/utility/pretty_print.py
fifids-0.1.1.dist-info/METADATA
fifids-0.1.1.dist-info/WHEEL
fifids-0.1.1.dist-info/RECORD
