Metadata-Version: 2.1
Name: fifids
Version: 0.1.1
Summary: data science for swiss cheese brains
Author: fibleep
Author-email: filipn924@gmail.com
Requires-Python: >=3.9,<4.0
Classifier: Programming Language :: Python :: 3
Classifier: Programming Language :: Python :: 3.9
Classifier: Programming Language :: Python :: 3.10
Classifier: Programming Language :: Python :: 3.11
Classifier: Programming Language :: Python :: 3.12
Requires-Dist: polars (>=0.20.18,<0.21.0)
Requires-Dist: pyarrow (>=15.0.2,<16.0.0)
Requires-Dist: scikit-learn (>=1.4.1.post1,<2.0.0)
Requires-Dist: seaborn (>=0.13.2,<0.14.0)
Requires-Dist: shap (>=0.45.0,<0.46.0)
Requires-Dist: statsmodels (>=0.14.1,<0.15.0)
Requires-Dist: xgboost (>=2.0.3,<3.0.0)
